alchemark_ai/__init__.py
alchemark_ai/main.py
alchemark_ai/configs/__init__.py
alchemark_ai/configs/logger.py
alchemark_ai/formatter/__init__.py
alchemark_ai/formatter/formatter_md.py
alchemark_ai/models/FormattedResult.py
alchemark_ai/models/PDFResult.py
alchemark_ai/models/__init__.py
alchemark_ai/pdf2md/__init__.py
alchemark_ai/pdf2md/pdf2md.py
alchemark_ai-0.1.9.dist-info/licenses/LICENSE
alchemark_ai-0.1.9.dist-info/METADATA
alchemark_ai-0.1.9.dist-info/WHEEL
alchemark_ai-0.1.9.dist-info/top_level.txt
alchemark_ai-0.1.9.dist-info/RECORD
