Metadata-Version: 2.4
Name: alchemark-ai
Version: 0.1.9
Summary: AlcheMark AI - PDF to Markdown conversion with rich metadata and element analysis
Author: Matheus Sena
License-Expression: MIT
Project-URL: Homepage, https://github.com/matthsena/AlcheMark-ai
Project-URL: Bug Tracker, https://github.com/matthsena/AlcheMark-ai/issues
Classifier: Programming Language :: Python :: 3
Classifier: Operating System :: OS Independent
Classifier: Development Status :: 4 - Beta
Classifier: Topic :: Text Processing :: Markup :: Markdown
Classifier: Topic :: Text Processing :: Markup :: LaTeX
Requires-Python: >=3.11
License-File: LICENSE
Requires-Dist: langdetect>=1.0.9
Requires-Dist: pydantic>=2.11.3
Requires-Dist: pymupdf>=1.25.5
Requires-Dist: pymupdf4llm>=0.0.21
Requires-Dist: tiktoken>=0.9.0
Provides-Extra: dev
Requires-Dist: pytest>=7.4.0; extra == "dev"
Requires-Dist: pytest-cov>=4.1.0; extra == "dev"
Dynamic: license-file
